HISTORY.rst
LICENSE
MANIFEST.in
README.rst
setup.cfg
setup.py
django_gov/__init__.py
django_gov/settings.py
django_gov/urls.py
django_gov.egg-info/PKG-INFO
django_gov.egg-info/SOURCES.txt
django_gov.egg-info/dependency_links.txt
django_gov.egg-info/requires.txt
django_gov.egg-info/top_level.txt
django_gov/management/__init__.py
django_gov/management/commands/__init__.py
django_gov/management/commands/update_gov_template.py
django_gov/static/images/apple-touch-icon-120x120.png
django_gov/static/images/apple-touch-icon-152x152.png
django_gov/static/images/apple-touch-icon-60x60.png
django_gov/static/images/apple-touch-icon-76x76.png
django_gov/static/images/favicon.ico
django_gov/static/images/gov.uk_logotype_crown.svg
django_gov/static/images/gov.uk_logotype_crown_invert.png
django_gov/static/images/gov.uk_logotype_crown_invert_trans.png
django_gov/static/images/opengraph-image.png
django_gov/static/javascripts/govuk-template.js
django_gov/static/javascripts/ie.js
django_gov/static/stylesheets/fonts-ie8.css
django_gov/static/stylesheets/fonts.css
django_gov/static/stylesheets/gov-swagger.css
django_gov/static/stylesheets/govuk-template-ie6.css
django_gov/static/stylesheets/govuk-template-ie7.css
django_gov/static/stylesheets/govuk-template-ie8.css
django_gov/static/stylesheets/govuk-template-print.css
django_gov/static/stylesheets/govuk-template.css
django_gov/static/stylesheets/fonts/GDSTransportTabular-Bold.eot
django_gov/static/stylesheets/fonts/GDSTransportTabular-Light.eot
django_gov/static/stylesheets/fonts/GDSTransportWebsite-Bold.eot
django_gov/static/stylesheets/fonts/GDSTransportWebsite.eot
django_gov/static/stylesheets/images/close.png
django_gov/static/stylesheets/images/gov.uk_logotype_crown-1x.png
django_gov/static/stylesheets/images/gov.uk_logotype_crown.png
django_gov/static/stylesheets/images/govuk-crest-2x.png
django_gov/static/stylesheets/images/govuk-crest-ie.png
django_gov/static/stylesheets/images/govuk-crest.png
django_gov/static/stylesheets/images/open-government-licence.png
django_gov/static/stylesheets/images/open-government-licence_2x.png
django_gov/templates/govuk_template/base.html
