Metadata-Version: 1.1
Name: django-gov
Version: 0.2.1
Summary: Base Django Application for MoJ Gov
Home-page: https://github.com/ministryofjustice/django-gov
Author: Josh Rowe
Author-email: josh.rowe@digital.justice.gov.uk
License: MIT License
Platform: UNKNOWN
Classifier: Development Status :: 4 - Beta
Classifier: Environment :: Web Environment
Classifier: Framework :: Django
Classifier: Intended Audience :: Developers
Classifier: License :: OSI Approved :: MIT License
Classifier: Operating System :: OS Independent
Classifier: Programming Language :: Python
Classifier: Topic :: Software Development :: Libraries :: Python Modules
